{
  "id": "1990:1079",
  "type": "statute",
  "title": "Lag (1990:1079) om tillfälliga bilförbud",
  "status": "in_force",
  "issued_date": "1990-11-15",
  "url": "https://data.riksdagen.se/dokument/sfs-1990-1079.html",
  "provisions": [
    {
      "provision_ref": "1",
      "section": "1",
      "content": "Regeringen eller efter regeringens bemyndigande en kommun får meddela föreskrifter om tillfälligt förbud mot trafik med person- och lastbilar inom vissa områden av kommunen, om luftföroreningarna i kommunen innebär akuta hälsorisker för dem som vistas där."
    },
    {
      "provision_ref": "2",
      "section": "2",
      "content": "Regeringen eller den myndighet som regeringen bestämmer får meddela närmare föreskrifter om vilka luftföroreningar som innebär akuta hälsorisker och om hur föroreningarna skall mätas."
    },
    {
      "provision_ref": "3",
      "section": "3",
      "content": "Om någon kör ett fordon i strid mot ett förbud enligt denna lag, får en polisman hindra fortsatt färd. Lag (2014:726)."
    }
  ]
}