{
  "id": "2002:179",
  "type": "statute",
  "title": "Lag (2002:179) om kreditering på skattekonto av tillfälligt sysselsättningsstöd till kommuner och regioner",
  "status": "in_force",
  "issued_date": "2002-04-18",
  "url": "https://data.riksdagen.se/dokument/sfs-2002-179.html",
  "provisions": [
    {
      "provision_ref": "1",
      "section": "1",
      "content": "Tillfälligt sysselsättningsstöd till kommuner och regioner som beslutats av Skatteverket ska tillgodoräknas kommunerna och regionerna genom kreditering på sådant skattekonto som avses i 61 kap. 1 § skatteförfarandelagen (2011:1244). Lag (2020:857)."
    }
  ]
}